odoo9_addon_openeducat_activity-9.0.2.4.0-py2.7-nspkg.pth
odoo_addons/openeducat_activity/activity_menu.xml
odoo_addons/openeducat_activity/__openerp__.py
odoo_addons/openeducat_activity/__init__.py
odoo_addons/openeducat_activity/security/ir.model.access.csv
odoo_addons/openeducat_activity/models/activity_type.py
odoo_addons/openeducat_activity/models/__init__.py
odoo_addons/openeducat_activity/models/student.py
odoo_addons/openeducat_activity/models/activity.py
odoo_addons/openeducat_activity/i18n/openeducat_activity.pot
odoo_addons/openeducat_activity/wizard/student_migrate_wizard.py
odoo_addons/openeducat_activity/wizard/student_migrate_wizard_view.xml
odoo_addons/openeducat_activity/wizard/__init__.py
odoo_addons/openeducat_activity/views/student_view.xml
odoo_addons/openeducat_activity/views/activity_type_view.xml
odoo_addons/openeducat_activity/views/activity_view.xml
odoo_addons/openeducat_activity/demo/op.activity.csv
odoo_addons/openeducat_activity/demo/op.activity.type.csv
odoo_addons/openeducat_activity/static/description/activity.png
odoo_addons/openeducat_activity/static/description/openeducat_logo.png
odoo_addons/openeducat_activity/static/description/index.html
odoo_addons/openeducat_activity/static/description/openeducat_activity_banner.jpg
odoo_addons/openeducat_activity/static/description/icon.png
odoo9_addon_openeducat_activity-9.0.2.4.0.dist-info/top_level.txt
odoo9_addon_openeducat_activity-9.0.2.4.0.dist-info/WHEEL
odoo9_addon_openeducat_activity-9.0.2.4.0.dist-info/RECORD
odoo9_addon_openeducat_activity-9.0.2.4.0.dist-info/metadata.json
odoo9_addon_openeducat_activity-9.0.2.4.0.dist-info/DESCRIPTION.rst
odoo9_addon_openeducat_activity-9.0.2.4.0.dist-info/METADATA
odoo9_addon_openeducat_activity-9.0.2.4.0.dist-info/namespace_packages.txt
